lbbutils
lbbutils/metrics
